brooks_mfc/__init__.py
brooks_mfc/__main__.py
brooks_mfc/driver.py
brooks_mfc/mock.py
brooks_mfc-0.1.4.dist-info/entry_points.txt
brooks_mfc-0.1.4.dist-info/LICENSE
brooks_mfc-0.1.4.dist-info/WHEEL
brooks_mfc-0.1.4.dist-info/METADATA
brooks_mfc-0.1.4.dist-info/RECORD
