Metadata-Version: 2.1
Name: brooks-mfc
Version: 0.1.4
Summary: Python driver for Brooks Instrument mass flow controllers
Home-page: http://github.com/numat/brooks_mfc/
Author: jamesjeffryes
Author-email: jamesgjeffryes@gmail.com
Requires-Python: >=3.6.1,<4.0.0
Classifier: Development Status :: 4 - Beta
Classifier: Natural Language :: English
Classifier: Programming Language :: Python :: 3
Classifier: Programming Language :: Python :: 3.7
Classifier: Programming Language :: Python :: 3.8
Classifier: Topic :: Scientific/Engineering :: Human Machine Interfaces
Requires-Dist: aiohttp (>=3.6.2,<4.0.0)
Project-URL: Repository, http://github.com/numat/brooks_mfc/
